bits/__init__.py
bits/leankit/__init__.py
bits/leankit/client.py
tests/__init__.py
bits_leankit-1.0.5.dist-info/LICENSE
bits_leankit-1.0.5.dist-info/METADATA
bits_leankit-1.0.5.dist-info/WHEEL
bits_leankit-1.0.5.dist-info/top_level.txt
bits_leankit-1.0.5.dist-info/RECORD
