Metadata-Version: 2.1
Name: bits-leankit
Version: 1.0.5
Summary: Leankit client library package for python
Home-page: https://github.com/broadinstitute/bits-leankit
Author: Lukas Karlsson
Author-email: karlsson@broadinstitute.org
License: BSD
Platform: UNKNOWN
Classifier: Programming Language :: Python
Classifier: Programming Language :: Python :: 2.7
Classifier: Programming Language :: Python :: 3
Classifier: Programming Language :: Python :: 3.5
Classifier: Programming Language :: Python :: 3.6
Classifier: Programming Language :: Python :: 3.7
Classifier: License :: OSI Approved :: BSD License
Classifier: Operating System :: OS Independent
Requires-Python: >=2.7, <4
